codenerix_storages/__init__.py
codenerix_storages/admin.py
codenerix_storages/apps.py
codenerix_storages/exceptions.py
codenerix_storages/forms.py
codenerix_storages/forms_stockcontrol.py
codenerix_storages/models.py
codenerix_storages/models_stockcontrol.py
codenerix_storages/settings.py
codenerix_storages/urls.py
codenerix_storages/urls_stockcontrol.py
codenerix_storages/views.py
codenerix_storages/views_stockcontrol.py
codenerix_storages/locale/en/LC_MESSAGES/django.po
codenerix_storages/locale/es/LC_MESSAGES/django.mo
codenerix_storages/locale/es/LC_MESSAGES/django.po
codenerix_storages/migrations/0001_initial.py
codenerix_storages/migrations/0002_auto_20180118_1040.py
codenerix_storages/migrations/0003_auto_20180118_1151.py
codenerix_storages/migrations/0004_auto_20180118_1358.py
codenerix_storages/migrations/0005_auto_20180118_1417.py
codenerix_storages/migrations/0006_auto_20180118_1724.py
codenerix_storages/migrations/0007_auto_20180118_1803.py
codenerix_storages/migrations/0008_auto_20180119_1029.py
codenerix_storages/migrations/0009_auto_20180119_1034.py
codenerix_storages/migrations/0010_auto_20180123_1316.py
codenerix_storages/migrations/0010_auto_20180125_0848.py
codenerix_storages/migrations/0011_merge_20180202_0726.py
codenerix_storages/migrations/0012_inventory_kind.py
codenerix_storages/migrations/0013_auto_20180216_1444.py
codenerix_storages/migrations/0014_inventoryinline_purchasesorder.py
codenerix_storages/migrations/0015_auto_20180219_1229.py
codenerix_storages/migrations/0016_auto_20180223_1846.py
codenerix_storages/migrations/0017_inventoryoutline_caducity.py
codenerix_storages/migrations/0018_auto_20180227_0858.py
codenerix_storages/migrations/0019_distribution_distributionline.py
codenerix_storages/migrations/0020_auto_20180413_1642.py
codenerix_storages/migrations/0021_auto_20180413_1825.py
codenerix_storages/migrations/0022_auto_20180414_0607.py
codenerix_storages/migrations/0023_auto_20180414_1252.py
django_codenerix_storages-4.0.1.dist-info/LICENSE
django_codenerix_storages-4.0.1.dist-info/METADATA
django_codenerix_storages-4.0.1.dist-info/WHEEL
django_codenerix_storages-4.0.1.dist-info/top_level.txt
django_codenerix_storages-4.0.1.dist-info/RECORD
